{
  "$ref": "#/$defs/StackPurpose",
  "$defs": {
    "StackPurpose": {
      "type": "string",
      "minLength": 2,
      "maxLength": 20,
      "pattern": "^[a-z][a-z0-9-]*$",
      "errorMessage": {
        "pattern": "Stack purpose must start with lowercase letter and contain only lowercase alphanumeric characters and hyphens"
      }
    }
  },
  "$schema": "https://json-schema.org/draft/2020-12/schema",
  "$id": "https://schemas.adaptiveworx.com/iac/stackpurpose.json",
  "title": "StackPurpose Schema",
  "description": "JSON Schema for StackPurpose validation in agent-optimized IaC deployments",
  "x-agent-optimized": true,
  "x-version": "1.0.0",
  "x-namespace": "adaptiveworx.iac"
}